PyBabeljs-0.0.8.dist-info/METADATA
PyBabeljs-0.0.8.dist-info/RECORD
PyBabeljs-0.0.8.dist-info/WHEEL
PyBabeljs-0.0.8.dist-info/top_level.txt
babeljs/__init__.py
babeljs/jscontext.py
babeljs/source.py
babeljs/transformer.py
babeljs/__pycache__/__init__.cpython-36.pyc
babeljs/static/babeljs/babel-plugin-transform-vue-jsx.min.js
babeljs/static/babeljs/browser.js
babeljs/static/regenerator/runtime.js
